bumpversion/__init__.py
bumpversion/bumper.py
bumpversion/constants.py
bumpversion/main.py
bumpversion/parser.py
bumpversion/replacer.py
bumpversion/schemas.py
bumpversion/serializer.py
bumpversion/settings.py
bumpversion/utils.py
bumpversion/vcs.py
bumpversion/tests/.pydocstylerc
bumpversion/tests/__init__.py
bumpversion/tests/test_bumper.py
bumpversion/tests/test_main.py
bumpversion/tests/test_parser.py
bumpversion/tests/test_schemas.py
bumpversion/tests/test_serializer.py
bumpversion/tests/test_utils.py
bumpversion/tests/utils.py
bump3version-0.1.0a1.dist-info/LICENSE
bump3version-0.1.0a1.dist-info/METADATA
bump3version-0.1.0a1.dist-info/WHEEL
bump3version-0.1.0a1.dist-info/entry_points.txt
bump3version-0.1.0a1.dist-info/top_level.txt
bump3version-0.1.0a1.dist-info/RECORD
