Metadata-Version: 2.1
Name: bump3version
Version: 0.1.0a1
Summary: Bumpversion - bump your project versions
Author: Jan Musílek
Author-email: jan.musilek@nic.cz
License: GPLv3+
Classifier: Development Status :: 2 - Pre-Alpha
Classifier: Intended Audience :: Developers
Classifier: License :: OSI Approved :: GNU General Public License v3 or later (GPLv3+)
Classifier: Operating System :: OS Independent
Classifier: Programming Language :: Python
Classifier: Programming Language :: Python :: 3.8
Classifier: Programming Language :: Python :: 3.9
Classifier: Programming Language :: Python :: 3.10
Classifier: Programming Language :: Python :: 3.11
Classifier: Topic :: Software Development :: Libraries
Classifier: Topic :: Software Development :: Libraries :: Python Modules
Classifier: Topic :: Utilities
Classifier: Typing :: Typed
Requires-Python: ~=3.8
License-File: LICENSE
Requires-Dist: click (~=8.1)
Requires-Dist: pydantic (~=1.9)
Requires-Dist: semver (~=3.0)
Requires-Dist: tomli (~=2.0)
Provides-Extra: quality
Requires-Dist: bandit ; extra == 'quality'
Requires-Dist: black ; extra == 'quality'
Requires-Dist: doc8 ; extra == 'quality'
Requires-Dist: flake8 ; extra == 'quality'
Requires-Dist: isort ; extra == 'quality'
Requires-Dist: mypy ; extra == 'quality'
Requires-Dist: pydocstyle ; extra == 'quality'
Provides-Extra: test
Requires-Dist: testfixtures ; extra == 'test'
